{
    "fluentMethods": true,
    "relationships": [
        {
            "relationshipType": "many-to-many",
            "relationshipValidateRules": "required",
            "relationshipName": "agenda",
            "otherEntityName": "agenda",
            "ownerSide": false,
            "otherEntityRelationshipName": "diaNoLaborable"
        }
    ],
    "fields": [
        {
            "fieldName": "fecha",
            "fieldType": "LocalDate"
        },
        {
            "fieldName": "dia",
            "fieldType": "Dia",
            "fieldValues": "LUNES,MARTES,MIERCOLES,JUEVES,VIERNES,SABADO,DOMINGO,TODOS"
        },
        {
            "fieldName": "repite",
            "fieldType": "Boolean"
        }
    ],
    "changelogDate": "20181123031252",
    "entityTableName": "dia_no_laborable",
    "dto": "mapstruct",
    "pagination": "no",
    "service": "serviceImpl",
    "jpaMetamodelFiltering": false
}